setup.py
dulo_probability/Binomialdistribution.py
dulo_probability/Gaussiandistribution.py
dulo_probability/Generaldistribution.py
dulo_probability/__init__.py
dulo_probability.egg-info/PKG-INFO
dulo_probability.egg-info/SOURCES.txt
dulo_probability.egg-info/dependency_links.txt
dulo_probability.egg-info/not-zip-safe
dulo_probability.egg-info/top_level.txt