Metadata-Version: 1.0
Name: dulo-probability
Version: 0.1
Summary: Gaussian and Binomial distributions
Home-page: UNKNOWN
Author: Job Dulo
Author-email: dulo.collins@gmail.com
License: UNKNOWN
Platform: UNKNOWN
